nad_receiver/__init__.py
nad_receiver/nad_commands.py
nad_receiver/nad_fake_transport.py
nad_receiver/nad_transport.py
nad_receiver-0.2.0.dist-info/LICENSE
nad_receiver-0.2.0.dist-info/METADATA
nad_receiver-0.2.0.dist-info/WHEEL
nad_receiver-0.2.0.dist-info/top_level.txt
nad_receiver-0.2.0.dist-info/zip-safe
nad_receiver-0.2.0.dist-info/RECORD
